py_common_util/__init__.py
py_common_util/blockchain/__init__.py
py_common_util/blockchain/blockchain.py
py_common_util/common/__init__.py
py_common_util/common/common_utils.py
py_common_util/common/date_utils.py
py_common_util/common/requests_utils.py
py_common_util/common/version.py
py_common_util/nlptoolkit/__init__.py
py_common_util/nlptoolkit/elmo/__init__.py
py_common_util/nlptoolkit/elmo/hello.py
py_common_util/nlptoolkit/elmo/train_elmo.py
py_common_util/nlptoolkit/elmo/bilm/__init__.py
py_common_util/nlptoolkit/elmo/bilm/data.py
py_common_util/nlptoolkit/elmo/bilm/elmo.py
py_common_util/nlptoolkit/elmo/bilm/model.py
py_common_util/nlptoolkit/elmo/bilm/training.py
py_common_util/pytorch/__init__.py
py_common_util/pytorch/torch_utils.py
py_common_util/tensorflow/__init__.py
py_common_util/tensorflow/tf_utils.py
py_common_util/tensorflow/tfrecord_utils.py
py_common_util/tensorflow/sample/__init__.py
py_common_util/tensorflow/sample/custom_estimator.py
py_common_util/tensorflow/sample/iris_data.py
py_common_util/tensorflow/sample/iris_test.csv
py_common_util/tensorflow/sample/iris_training.csv
py_common_util/tushare/__init__.py
py_common_util/tushare/mysql_utils.py
py_common_util/tushare/pandas_utils.py
py_common_util/tushare/talib_utils.py
py_common_util/tushare/tushare_wrapper.py
py_common_util-0.0.41.dist-info/LICENSE
py_common_util-0.0.41.dist-info/METADATA
py_common_util-0.0.41.dist-info/WHEEL
py_common_util-0.0.41.dist-info/top_level.txt
py_common_util-0.0.41.dist-info/RECORD
