Metadata-Version: 2.1
Name: py-common-util
Version: 0.0.41
Summary: UNKNOWN
Home-page: UNKNOWN
Author: tony
Author-email: UNKNOWN
License: BSD
Keywords: python common util
Platform: UNKNOWN
Classifier: Development Status :: 4 - Beta
Classifier: Programming Language :: Python :: 2.6
Classifier: Programming Language :: Python :: 2.7
Classifier: Programming Language :: Python :: 3.2
Classifier: Programming Language :: Python :: 3.3
Classifier: Programming Language :: Python :: 3.4
Classifier: Programming Language :: Python :: 3.5
Classifier: Programming Language :: Python :: 3.6
Classifier: License :: OSI Approved :: BSD License
Requires-Dist: requests (>=2.18.4)
